AUTHORS
LICENSE
MANIFEST.in
README.rst
setup.py
Coffin.egg-info/PKG-INFO
Coffin.egg-info/SOURCES.txt
Coffin.egg-info/dependency_links.txt
Coffin.egg-info/top_level.txt
coffin/__init__.py
coffin/common.py
coffin/interop.py
coffin/static.py
coffin/staticfiles.py
tests/__init__.py
tests/test_defaultags.py