Metadata-Version: 1.1
Name: Coffin
Version: 2.0.0
Summary: Jinja2 adapter for Django
Home-page: http://github.com/coffin/coffin
Author: Michael Elsdoerfer
Author-email: michael@elsdoerfer.com
License: UNKNOWN
Platform: UNKNOWN
Classifier: Framework :: Django
Classifier: Intended Audience :: Developers
Classifier: Intended Audience :: System Administrators
Classifier: Operating System :: OS Independent
Classifier: Topic :: Software Development
